qif/__init__.py
qif/__init__.pyi
qif/_qif.cpython-312-x86_64-linux-gnu.so
qif/libarmadillo.so
qif/libarmadillo.so.15
qif/libarmadillo.so.15.0.1
qif/libmp++.so
qif/libmp++.so.16
qif/libmp++.so.16.0
qif/libqif.so
qif/lp.pyi
qif/probab.pyi
qif/refinement.pyi
qif/typing.py
qif/utility.pyi
qif/.libs/libamd-a26d1aab.so.2.4.1
qif/.libs/libarmadillo-6cbf0848.so.15.0.1
qif/.libs/libcolamd-dc193ab4.so.2.9.1
qif/.libs/libglpk-49b4dd37.so.40.3.0
qif/.libs/libgmp-d944b113.so.10.3.2
qif/.libs/libgsl-b64c76bc.so.23.1.0
qif/.libs/libgslcblas-cd2c2030.so.0.0.0
qif/.libs/libmp++-9c545dd5.so.16.0
qif/.libs/libqif-a9148f4f.so
qif/.libs/libsuitesparseconfig-e4e8c4aa.so.4.4.4
qif/channel/__init__.py
qif/channel/__init__.pyi
qif/channel/compose.pyi
qif/measure/__init__.py
qif/measure/__init__.pyi
qif/measure/bayes_risk.pyi
qif/measure/bayes_vuln.pyi
qif/measure/d_privacy.pyi
qif/measure/g_vuln.pyi
qif/measure/guessing.pyi
qif/measure/l_risk.pyi
qif/measure/pred_risk.pyi
qif/measure/pred_vuln.pyi
qif/measure/shannon.pyi
qif/mechanism/__init__.py
qif/mechanism/__init__.pyi
qif/mechanism/bayes_risk.pyi
qif/mechanism/bayes_vuln.pyi
qif/mechanism/d_privacy.pyi
qif/mechanism/g_vuln.pyi
qif/mechanism/geo_ind.pyi
qif/mechanism/l_risk.pyi
qif/mechanism/shannon.pyi
qif/metric/__init__.py
qif/metric/__init__.pyi
qif/metric/optimize.pyi
qif-2.0.dist-info/METADATA
qif-2.0.dist-info/WHEEL
qif-2.0.dist-info/top_level.txt
qif-2.0.dist-info/RECORD
