Metadata-Version: 2.2
Name: qiftmp
Version: 2.0
Summary: Quantitative Information Flow library
Home-page: https://github.com/chatziko/libqif
Author: Kostas Chatzikokolakis
Author-email: kostas@chatzi.org
Project-URL: Bug Tracker, https://github.com/chatziko/libqif/issues
Project-URL: Documentation, http://chatziko.github.io/libqif/
Project-URL: Source Code, https://github.com/chatziko/libqif
Requires-Dist: numpy
Dynamic: author
Dynamic: author-email
Dynamic: description
Dynamic: description-content-type
Dynamic: home-page
Dynamic: project-url
Dynamic: requires-dist
Dynamic: summary
